[{"\ufeffein": "390806351", "tax_pd": "201812", "subseccd": "3", "s501c3or4947a1cd": "Y", "schdbind": "Y", "politicalactvtscd": "N", "lbbyingactvtscd": "N", "subjto6033cd": "N", "dnradvisedfundscd": "N", "prptyintrcvdcd": "N", "maintwrkofartcd": "N", "crcounselingqstncd": "N", "hldassetsintermpermcd": "Y", "rptlndbldgeqptcd": "Y", "rptinvstothsecd": "N", "rptinvstprgrelcd": "N", "rptothasstcd": "N", "rptothliabcd": "N", "sepcnsldtfinstmtcd": "N", "sepindaudfinstmtcd": "Y", "inclinfinstmtcd": "N", "operateschools170cd": "N", "frgnofficecd": "N", "frgnrevexpnscd": "N", "frgngrntscd": "N", "frgnaggragrntscd": "N", "rptprofndrsngfeescd": "N", "rptincfnndrsngcd": "Y", "rptincgamingcd": "N", "operatehosptlcd": "N", "hospaudfinstmtcd": "N", "rptgrntstogovtcd": "N", "rptgrntstoindvcd": "N", "rptyestocompnstncd": "N", "txexmptbndcd": "N", "invstproceedscd": "N", "maintescrwaccntcd": "N", "actonbehalfcd": "N", "engageexcessbnftcd": "N", "awarexcessbnftcd": "N", "loantofficercd": "N", "grantoofficercd": "N", "dirbusnreltdcd": "N", "fmlybusnreltdcd": "N", "servasofficercd": "N", "recvnoncashcd": "N", "recvartcd": "N", "ceaseoperationscd": "N", "sellorexchcd": "N", "ownsepentcd": "N", "reltdorgcd": "Y", "intincntrlcd": "N", "orgtrnsfrcd": "N", "conduct5percentcd": "N", "compltschocd": "Y", "f1096cnt": "16", "fw2gcnt": "0", "wthldngrulescd": "N", "noemplyeesw3cnt": "734", "filerqrdrtnscd": "Y", "unrelbusinccd": "N", "filedf990tcd": "N", "frgnacctcd": "N", "prohibtdtxshltrcd": "N", "prtynotifyorgcd": "N", "filedf8886tcd": "N", "solicitcntrbcd": "N", "exprstmntcd": "N", "providegoodscd": "N", "notfydnrvalcd": "N", "filedf8282cd": "N", "f8282cnt": "0", "fndsrcvdcd": "N", "premiumspaidcd": "N", "filedf8899cd": "N", "filedf1098ccd": "N", "excbushldngscd": "N", "s4966distribcd": "N", "distribtodonorcd": "N", "initiationfees": "0", "grsrcptspublicuse": "0", "grsincmembers": "0", "grsincother": "0", "filedlieuf1041cd": "N", "txexmptint": "0", "qualhlthplncd": "N", "qualhlthreqmntn": "0", "qualhlthonhnd": "0", "rcvdpdtngcd": "N", "filedf720cd": "N", "totreprtabled": "125901", "totcomprelatede": "0", "totestcompf": "44188", "noindiv100kcnt": "0", "nocontractor100kcnt": "0", "totcntrbgfts": "10680538", "prgmservcode2acd": "624410", "totrev2acola": "1530786", "prgmservcode2bcd": "713940", "totrev2bcola": "1275042", "prgmservcode2ccd": "713940", "totrev2ccola": "773081", "prgmservcode2dcd": "900099", "totrev2dcola": "744584", "prgmservcode2ecd": "713940", "totrev2ecola": "597887", "totrev2fcola": "177636", "totprgmrevnue": "5099016", "invstmntinc": "6672", "txexmptbndsproceeds": "0", "royaltsinc": "0", "grsrntsreal": "5633", "grsrntsprsnl": "0", "rntlexpnsreal": "0", "rntlexpnsprsnl": "0", "rntlincreal": "5633", "rntlincprsnl": "0", "netrntlinc": "5633", "grsalesecur": "0", "grsalesothr": "0", "cstbasisecur": "0", "cstbasisothr": "64579", "gnlsecur": "0", "gnlsothr": "-64579", "netgnls": "-64579", "grsincfndrsng": "6850", "lessdirfndrsng": "36608", "netincfndrsng": "-29758", "grsincgaming": "0", "lessdirgaming": "0", "netincgaming": "0", "grsalesinvent": "98531", "lesscstofgoods": "57635", "netincsales": "40896", "miscrev11acd": "", "miscrevtota": "0", "miscrev11bcd": "", "miscrevtot11b": "0", "miscrev11ccd": "", "miscrevtot11c": "0", "miscrevtot11d": "8155", "miscrevtot11e": "8155", "totrevenue": "15746573", "grntstogovt": "0", "grnsttoindiv": "0", "grntstofrgngovt": "0", "benifitsmembrs": "0", "compnsatncurrofcr": "170089", "compnsatnandothr": "2860304", "othrsalwages": "0", "pensionplancontrb": "62465", "othremplyeebenef": "289871", "payrolltx": "214408", "feesforsrvcmgmt": "0", "legalfees": "0", "accntingfees": "0", "feesforsrvclobby": "0", "profndraising": "0", "feesforsrvcinvstmgmt": "0", "feesforsrvcothr": "107357", "advrtpromo": "42173", "officexpns": "24010", "infotech": "0", "royaltsexpns": "0", "occupancy": "384946", "travel": "45530", "travelofpublicoffcl": "0", "converconventmtng": "0", "interestamt": "37758", "pymtoaffiliates": "0", "deprcatndepletn": "459764", "insurance": "72132", "othrexpnsa": "508936", "othrexpnsb": "362568", "othrexpnsc": "203487", "othrexpnsd": "139254", "othrexpnse": "0", "othrexpnsf": "100784", "totfuncexpns": "6085836", "nonintcashend": "568485", "svngstempinvend": "1478038", "pldgegrntrcvblend": "68537", "accntsrcvblend": "897527", "currfrmrcvblend": "0", "rcvbldisqualend": "0", "notesloansrcvblend": "800000", "invntriesalesend": "27482", "prepaidexpnsend": "23153", "lndbldgsequipend": "15609266", "invstmntsend": "0", "invstmntsothrend": "0", "invstmntsprgmend": "0", "intangibleassetsend": "0", "othrassetsend": "297778", "totassetsend": "19770266", "accntspayableend": "346059", "grntspayableend": "0", "deferedrevnuend": "900198", "txexmptbndsend": "0", "escrwaccntliabend": "0", "paybletoffcrsend": "0", "secrdmrtgsend": "495511", "unsecurednotesend": "0", "othrliabend": "0", "totliabend": "1741768", "unrstrctnetasstsend": "17310190", "temprstrctnetasstsend": "718308", "permrstrctnetasstsend": "0", "capitalstktrstend": "0", "paidinsurplusend": "0", "retainedearnend": "0", "totnetassetend": "18028498", "totnetliabastend": "19770266", "nonpfrea": "9", "totnooforgscnt": "0", "totsupport": "0", "gftgrntsrcvd170": "0", "txrevnuelevied170": "0", "srvcsval170": "0", "pubsuppsubtot170": "0", "exceeds2pct170": "0", "pubsupplesspct170": "0", "samepubsuppsubtot170": "0", "grsinc170": "0", "netincunreltd170": "0", "othrinc170": "0", "totsupp170": "0", "grsrcptsrelated170": "0", "totgftgrntrcvd509": "13304876", "grsrcptsadmissn509": "24449682", "grsrcptsactivities509": "240095", "txrevnuelevied509": "0", "srvcsval509": "0", "pubsuppsubtot509": "37994653", "rcvdfrmdisqualsub509": "945320", "exceeds1pct509": "0", "subtotpub509": "945320", "pubsupplesub509": "37049333", "samepubsuppsubtot509": "37994653", "grsinc509": "34191", "unreltxincls511tx509": "0", "subtotsuppinc509": "34191", "netincunrelatd509": "0", "othrinc509": "0", "totsupp509": "38028844"}]