[{"\ufeffein": "416175999", "tax_pd": "201812", "subseccd": "3", "s501c3or4947a1cd": "Y", "schdbind": "Y", "politicalactvtscd": "N", "lbbyingactvtscd": "N", "subjto6033cd": "N", "dnradvisedfundscd": "N", "prptyintrcvdcd": "N", "maintwrkofartcd": "N", "crcounselingqstncd": "N", "hldassetsintermpermcd": "N", "rptlndbldgeqptcd": "Y", "rptinvstothsecd": "N", "rptinvstprgrelcd": "N", "rptothasstcd": "N", "rptothliabcd": "Y", "sepcnsldtfinstmtcd": "Y", "sepindaudfinstmtcd": "Y", "inclinfinstmtcd": "N", "operateschools170cd": "N", "frgnofficecd": "N", "frgnrevexpnscd": "N", "frgngrntscd": "N", "frgnaggragrntscd": "N", "rptprofndrsngfeescd": "N", "rptincfnndrsngcd": "Y", "rptincgamingcd": "N", "operatehosptlcd": "N", "hospaudfinstmtcd": "N", "rptgrntstogovtcd": "N", "rptgrntstoindvcd": "Y", "rptyestocompnstncd": "N", "txexmptbndcd": "N", "invstproceedscd": "N", "maintescrwaccntcd": "N", "actonbehalfcd": "N", "engageexcessbnftcd": "N", "awarexcessbnftcd": "N", "loantofficercd": "N", "grantoofficercd": "N", "dirbusnreltdcd": "N", "fmlybusnreltdcd": "N", "servasofficercd": "N", "recvnoncashcd": "Y", "recvartcd": "N", "ceaseoperationscd": "N", "sellorexchcd": "N", "ownsepentcd": "N", "reltdorgcd": "N", "intincntrlcd": "N", "orgtrnsfrcd": "N", "conduct5percentcd": "N", "compltschocd": "Y", "f1096cnt": "80", "fw2gcnt": "0", "wthldngrulescd": "Y", "noemplyeesw3cnt": "26", "filerqrdrtnscd": "Y", "unrelbusinccd": "Y", "filedf990tcd": "Y", "frgnacctcd": "N", "prohibtdtxshltrcd": "N", "prtynotifyorgcd": "N", "filedf8886tcd": "N", "solicitcntrbcd": "N", "exprstmntcd": "N", "providegoodscd": "Y", "notfydnrvalcd": "Y", "filedf8282cd": "N", "f8282cnt": "0", "fndsrcvdcd": "N", "premiumspaidcd": "N", "filedf8899cd": "N", "filedf1098ccd": "N", "excbushldngscd": "N", "s4966distribcd": "N", "distribtodonorcd": "N", "initiationfees": "0", "grsrcptspublicuse": "0", "grsincmembers": "0", "grsincother": "0", "filedlieuf1041cd": "N", "txexmptint": "0", "qualhlthplncd": "N", "qualhlthreqmntn": "0", "qualhlthonhnd": "0", "rcvdpdtngcd": "N", "filedf720cd": "N", "totreprtabled": "62833", "totcomprelatede": "0", "totestcompf": "8436", "noindiv100kcnt": "0", "nocontractor100kcnt": "0", "totcntrbgfts": "8987852", "prgmservcode2acd": "900099", "totrev2acola": "62800", "prgmservcode2bcd": "", "totrev2bcola": "0", "prgmservcode2ccd": "", "totrev2ccola": "0", "prgmservcode2dcd": "", "totrev2dcola": "0", "prgmservcode2ecd": "", "totrev2ecola": "0", "totrev2fcola": "0", "totprgmrevnue": "62800", "invstmntinc": "84", "txexmptbndsproceeds": "0", "royaltsinc": "0", "grsrntsreal": "315293", "grsrntsprsnl": "61111", "rntlexpnsreal": "0", "rntlexpnsprsnl": "0", "rntlincreal": "315293", "rntlincprsnl": "61111", "netrntlinc": "376404", "grsalesecur": "0", "grsalesothr": "0", "cstbasisecur": "0", "cstbasisothr": "0", "gnlsecur": "0", "gnlsothr": "0", "netgnls": "0", "grsincfndrsng": "16570", "lessdirfndrsng": "75279", "netincfndrsng": "-58709", "grsincgaming": "0", "lessdirgaming": "0", "netincgaming": "0", "grsalesinvent": "0", "lesscstofgoods": "0", "netincsales": "0", "miscrev11acd": "900099", "miscrevtota": "11171", "miscrev11bcd": "", "miscrevtot11b": "0", "miscrev11ccd": "", "miscrevtot11c": "0", "miscrevtot11d": "0", "miscrevtot11e": "11171", "totrevenue": "9379602", "grntstogovt": "0", "grnsttoindiv": "7440812", "grntstofrgngovt": "0", "benifitsmembrs": "0", "compnsatncurrofcr": "71269", "compnsatnandothr": "0", "othrsalwages": "841147", "pensionplancontrb": "27383", "othremplyeebenef": "81772", "payrolltx": "75211", "feesforsrvcmgmt": "0", "legalfees": "12500", "accntingfees": "15575", "feesforsrvclobby": "0", "profndraising": "0", "feesforsrvcinvstmgmt": "0", "feesforsrvcothr": "105392", "advrtpromo": "11826", "officexpns": "135766", "infotech": "9391", "royaltsexpns": "0", "occupancy": "109143", "travel": "14572", "travelofpublicoffcl": "0", "converconventmtng": "5021", "interestamt": "130351", "pymtoaffiliates": "0", "deprcatndepletn": "179742", "insurance": "61934", "othrexpnsa": "20399", "othrexpnsb": "16444", "othrexpnsc": "14128", "othrexpnsd": "12666", "othrexpnse": "0", "othrexpnsf": "4967", "totfuncexpns": "9397411", "nonintcashend": "602916", "svngstempinvend": "190504", "pldgegrntrcvblend": "106250", "accntsrcvblend": "38015", "currfrmrcvblend": "0", "rcvbldisqualend": "0", "notesloansrcvblend": "0", "invntriesalesend": "245848", "prepaidexpnsend": "28202", "lndbldgsequipend": "4699720", "invstmntsend": "0", "invstmntsothrend": "0", "invstmntsprgmend": "0", "intangibleassetsend": "0", "othrassetsend": "0", "totassetsend": "5911455", "accntspayableend": "115289", "grntspayableend": "0", "deferedrevnuend": "0", "txexmptbndsend": "0", "escrwaccntliabend": "0", "paybletoffcrsend": "0", "secrdmrtgsend": "3953717", "unsecurednotesend": "0", "othrliabend": "4892", "totliabend": "4073898", "unrstrctnetasstsend": "1747557", "temprstrctnetasstsend": "90000", "permrstrctnetasstsend": "0", "capitalstktrstend": "0", "paidinsurplusend": "0", "retainedearnend": "0", "totnetassetend": "1837557", "totnetliabastend": "5911455", "nonpfrea": "7", "totnooforgscnt": "0", "totsupport": "0", "gftgrntsrcvd170": "45255598", "txrevnuelevied170": "0", "srvcsval170": "0", "pubsuppsubtot170": "45255598", "exceeds2pct170": "0", "pubsupplesspct170": "45255598", "samepubsuppsubtot170": "45255598", "grsinc170": "1546614", "netincunreltd170": "265351", "othrinc170": "0", "totsupp170": "47067563", "grsrcptsrelated170": "691449", "totgftgrntrcvd509": "0", "grsrcptsadmissn509": "0", "grsrcptsactivities509": "0", "txrevnuelevied509": "0", "srvcsval509": "0", "pubsuppsubtot509": "0", "rcvdfrmdisqualsub509": "0", "exceeds1pct509": "0", "subtotpub509": "0", "pubsupplesub509": "0", "samepubsuppsubtot509": "0", "grsinc509": "0", "unreltxincls511tx509": "0", "subtotsuppinc509": "0", "netincunrelatd509": "0", "othrinc509": "0", "totsupp509": "0"}]