[{"\ufeffein": "431825029", "tax_pd": "201805", "subseccd": "3", "s501c3or4947a1cd": "Y", "schdbind": "Y", "politicalactvtscd": "N", "lbbyingactvtscd": "N", "subjto6033cd": "N", "dnradvisedfundscd": "N", "prptyintrcvdcd": "N", "maintwrkofartcd": "N", "crcounselingqstncd": "N", "hldassetsintermpermcd": "N", "rptlndbldgeqptcd": "Y", "rptinvstothsecd": "N", "rptinvstprgrelcd": "N", "rptothasstcd": "N", "rptothliabcd": "Y", "sepcnsldtfinstmtcd": "Y", "sepindaudfinstmtcd": "N", "inclinfinstmtcd": "Y", "operateschools170cd": "N", "frgnofficecd": "N", "frgnrevexpnscd": "N", "frgngrntscd": "N", "frgnaggragrntscd": "N", "rptprofndrsngfeescd": "N", "rptincfnndrsngcd": "N", "rptincgamingcd": "N", "operatehosptlcd": "N", "hospaudfinstmtcd": "N", "rptgrntstogovtcd": "Y", "rptgrntstoindvcd": "N", "rptyestocompnstncd": "Y", "txexmptbndcd": "Y", "invstproceedscd": "N", "maintescrwaccntcd": "N", "actonbehalfcd": "N", "engageexcessbnftcd": "N", "awarexcessbnftcd": "N", "loantofficercd": "N", "grantoofficercd": "N", "dirbusnreltdcd": "N", "fmlybusnreltdcd": "N", "servasofficercd": "N", "recvnoncashcd": "N", "recvartcd": "N", "ceaseoperationscd": "N", "sellorexchcd": "N", "ownsepentcd": "N", "reltdorgcd": "Y", "intincntrlcd": "N", "orgtrnsfrcd": "N", "conduct5percentcd": "N", "compltschocd": "Y", "f1096cnt": "33", "fw2gcnt": "0", "wthldngrulescd": "N", "noemplyeesw3cnt": "179", "filerqrdrtnscd": "Y", "unrelbusinccd": "N", "filedf990tcd": "N", "frgnacctcd": "N", "prohibtdtxshltrcd": "N", "prtynotifyorgcd": "N", "filedf8886tcd": "N", "solicitcntrbcd": "N", "exprstmntcd": "N", "providegoodscd": "N", "notfydnrvalcd": "N", "filedf8282cd": "N", "f8282cnt": "0", "fndsrcvdcd": "N", "premiumspaidcd": "N", "filedf8899cd": "N", "filedf1098ccd": "N", "excbushldngscd": "N", "s4966distribcd": "N", "distribtodonorcd": "N", "initiationfees": "0", "grsrcptspublicuse": "0", "grsincmembers": "0", "grsincother": "0", "filedlieuf1041cd": "N", "txexmptint": "0", "qualhlthplncd": "N", "qualhlthreqmntn": "0", "qualhlthonhnd": "0", "rcvdpdtngcd": "N", "filedf720cd": "N", "totreprtabled": "70500", "totcomprelatede": "943864", "totestcompf": "73941", "noindiv100kcnt": "0", "nocontractor100kcnt": "2", "totcntrbgfts": "20200", "prgmservcode2acd": "900099", "totrev2acola": "9773365", "prgmservcode2bcd": "", "totrev2bcola": "0", "prgmservcode2ccd": "", "totrev2ccola": "0", "prgmservcode2dcd": "", "totrev2dcola": "0", "prgmservcode2ecd": "", "totrev2ecola": "0", "totrev2fcola": "0", "totprgmrevnue": "9773365", "invstmntinc": "348603", "txexmptbndsproceeds": "0", "royaltsinc": "0", "grsrntsreal": "0", "grsrntsprsnl": "0", "rntlexpnsreal": "0", "rntlexpnsprsnl": "0", "rntlincreal": "0", "rntlincprsnl": "0", "netrntlinc": "0", "grsalesecur": "238149", "grsalesothr": "50000", "cstbasisecur": "0", "cstbasisothr": "42546", "gnlsecur": "238149", "gnlsothr": "7454", "netgnls": "245603", "grsincfndrsng": "0", "lessdirfndrsng": "0", "netincfndrsng": "0", "grsincgaming": "0", "lessdirgaming": "0", "netincgaming": "0", "grsalesinvent": "0", "lesscstofgoods": "0", "netincsales": "0", "miscrev11acd": "623000", "miscrevtota": "51709", "miscrev11bcd": "623000", "miscrevtot11b": "43261", "miscrev11ccd": "623000", "miscrevtot11c": "3132", "miscrevtot11d": "3042", "miscrevtot11e": "101144", "totrevenue": "10488915", "grntstogovt": "155885", "grnsttoindiv": "0", "grntstofrgngovt": "0", "benifitsmembrs": "0", "compnsatncurrofcr": "71786", "compnsatnandothr": "0", "othrsalwages": "2582722", "pensionplancontrb": "0", "othremplyeebenef": "513556", "payrolltx": "225864", "feesforsrvcmgmt": "487887", "legalfees": "2243", "accntingfees": "30775", "feesforsrvclobby": "0", "profndraising": "0", "feesforsrvcinvstmgmt": "0", "feesforsrvcothr": "100080", "advrtpromo": "247506", "officexpns": "695111", "infotech": "148068", "royaltsexpns": "0", "occupancy": "919853", "travel": "18422", "travelofpublicoffcl": "0", "converconventmtng": "14329", "interestamt": "891508", "pymtoaffiliates": "0", "deprcatndepletn": "1024580", "insurance": "169701", "othrexpnsa": "529164", "othrexpnsb": "13070", "othrexpnsc": "0", "othrexpnsd": "0", "othrexpnse": "0", "othrexpnsf": "0", "totfuncexpns": "8842110", "nonintcashend": "1177158", "svngstempinvend": "0", "pldgegrntrcvblend": "0", "accntsrcvblend": "115979", "currfrmrcvblend": "0", "rcvbldisqualend": "0", "notesloansrcvblend": "0", "invntriesalesend": "22089", "prepaidexpnsend": "66786", "lndbldgsequipend": "15186337", "invstmntsend": "21916143", "invstmntsothrend": "71687", "invstmntsprgmend": "0", "intangibleassetsend": "0", "othrassetsend": "0", "totassetsend": "38556179", "accntspayableend": "1086890", "grntspayableend": "0", "deferedrevnuend": "562644", "txexmptbndsend": "16425206", "escrwaccntliabend": "0", "paybletoffcrsend": "0", "secrdmrtgsend": "0", "unsecurednotesend": "0", "othrliabend": "6902380", "totliabend": "24977120", "unrstrctnetasstsend": "13579059", "temprstrctnetasstsend": "0", "permrstrctnetasstsend": "0", "capitalstktrstend": "0", "paidinsurplusend": "0", "retainedearnend": "0", "totnetassetend": "13579059", "totnetliabastend": "38556179", "nonpfrea": "9", "totnooforgscnt": "0", "totsupport": "0", "gftgrntsrcvd170": "0", "txrevnuelevied170": "0", "srvcsval170": "0", "pubsuppsubtot170": "0", "exceeds2pct170": "0", "pubsupplesspct170": "0", "samepubsuppsubtot170": "0", "grsinc170": "0", "netincunreltd170": "0", "othrinc170": "0", "totsupp170": "0", "grsrcptsrelated170": "0", "totgftgrntrcvd509": "29010", "grsrcptsadmissn509": "45408693", "grsrcptsactivities509": "0", "txrevnuelevied509": "0", "srvcsval509": "0", "pubsuppsubtot509": "45437703", "rcvdfrmdisqualsub509": "0", "exceeds1pct509": "0", "subtotpub509": "0", "pubsupplesub509": "45437703", "samepubsuppsubtot509": "45437703", "grsinc509": "2056637", "unreltxincls511tx509": "0", "subtotsuppinc509": "2056637", "netincunrelatd509": "0", "othrinc509": "376311", "totsupp509": "47870651"}]