[{"\ufeffein": "480441812", "tax_pd": "201812", "subseccd": "12", "s501c3or4947a1cd": "N", "schdbind": "N", "politicalactvtscd": "N", "lbbyingactvtscd": "N", "subjto6033cd": "N", "dnradvisedfundscd": "N", "prptyintrcvdcd": "N", "maintwrkofartcd": "N", "crcounselingqstncd": "N", "hldassetsintermpermcd": "N", "rptlndbldgeqptcd": "Y", "rptinvstothsecd": "N", "rptinvstprgrelcd": "Y", "rptothasstcd": "N", "rptothliabcd": "Y", "sepcnsldtfinstmtcd": "Y", "sepindaudfinstmtcd": "Y", "inclinfinstmtcd": "N", "operateschools170cd": "N", "frgnofficecd": "N", "frgnrevexpnscd": "N", "frgngrntscd": "N", "frgnaggragrntscd": "N", "rptprofndrsngfeescd": "N", "rptincfnndrsngcd": "N", "rptincgamingcd": "N", "operatehosptlcd": "N", "hospaudfinstmtcd": "N", "rptgrntstogovtcd": "N", "rptgrntstoindvcd": "N", "rptyestocompnstncd": "Y", "txexmptbndcd": "N", "invstproceedscd": "N", "maintescrwaccntcd": "N", "actonbehalfcd": "N", "engageexcessbnftcd": "N", "awarexcessbnftcd": "N", "loantofficercd": "N", "grantoofficercd": "N", "dirbusnreltdcd": "N", "fmlybusnreltdcd": "Y", "servasofficercd": "N", "recvnoncashcd": "N", "recvartcd": "N", "ceaseoperationscd": "N", "sellorexchcd": "N", "ownsepentcd": "N", "reltdorgcd": "N", "intincntrlcd": "N", "orgtrnsfrcd": "N", "conduct5percentcd": "N", "compltschocd": "Y", "f1096cnt": "57", "fw2gcnt": "0", "wthldngrulescd": "Y", "noemplyeesw3cnt": "14", "filerqrdrtnscd": "Y", "unrelbusinccd": "N", "filedf990tcd": "N", "frgnacctcd": "N", "prohibtdtxshltrcd": "N", "prtynotifyorgcd": "N", "filedf8886tcd": "N", "solicitcntrbcd": "N", "exprstmntcd": "N", "providegoodscd": "N", "notfydnrvalcd": "N", "filedf8282cd": "N", "f8282cnt": "0", "fndsrcvdcd": "N", "premiumspaidcd": "N", "filedf8899cd": "N", "filedf1098ccd": "N", "excbushldngscd": "N", "s4966distribcd": "N", "distribtodonorcd": "N", "initiationfees": "0", "grsrcptspublicuse": "0", "grsincmembers": "12734659", "grsincother": "249234", "filedlieuf1041cd": "N", "txexmptint": "0", "qualhlthplncd": "N", "qualhlthreqmntn": "0", "qualhlthonhnd": "0", "rcvdpdtngcd": "N", "filedf720cd": "N", "totreprtabled": "426611", "totcomprelatede": "0", "totestcompf": "202101", "noindiv100kcnt": "2", "nocontractor100kcnt": "2", "totcntrbgfts": "0", "prgmservcode2acd": "221000", "totrev2acola": "12385139", "prgmservcode2bcd": "221000", "totrev2bcola": "175396", "prgmservcode2ccd": "", "totrev2ccola": "0", "prgmservcode2dcd": "", "totrev2dcola": "0", "prgmservcode2ecd": "", "totrev2ecola": "0", "totrev2fcola": "0", "totprgmrevnue": "12560535", "invstmntinc": "30053", "txexmptbndsproceeds": "0", "royaltsinc": "0", "grsrntsreal": "0", "grsrntsprsnl": "13662", "rntlexpnsreal": "0", "rntlexpnsprsnl": "0", "rntlincreal": "0", "rntlincprsnl": "13662", "netrntlinc": "13662", "grsalesecur": "0", "grsalesothr": "0", "cstbasisecur": "0", "cstbasisothr": "0", "gnlsecur": "0", "gnlsothr": "0", "netgnls": "0", "grsincfndrsng": "0", "lessdirfndrsng": "0", "netincfndrsng": "0", "grsincgaming": "0", "lessdirgaming": "0", "netincgaming": "0", "grsalesinvent": "0", "lesscstofgoods": "0", "netincsales": "0", "miscrev11acd": "221000", "miscrevtota": "30123", "miscrev11bcd": "", "miscrevtot11b": "0", "miscrev11ccd": "", "miscrevtot11c": "0", "miscrevtot11d": "0", "miscrevtot11e": "30123", "totrevenue": "12634373", "grntstogovt": "0", "grnsttoindiv": "0", "grntstofrgngovt": "0", "benifitsmembrs": "1084866", "compnsatncurrofcr": "458142", "compnsatnandothr": "0", "othrsalwages": "0", "pensionplancontrb": "0", "othremplyeebenef": "0", "payrolltx": "0", "feesforsrvcmgmt": "0", "legalfees": "0", "accntingfees": "0", "feesforsrvclobby": "0", "profndraising": "0", "feesforsrvcinvstmgmt": "0", "feesforsrvcothr": "0", "advrtpromo": "0", "officexpns": "0", "infotech": "0", "royaltsexpns": "0", "occupancy": "0", "travel": "0", "travelofpublicoffcl": "0", "converconventmtng": "0", "interestamt": "536420", "pymtoaffiliates": "0", "deprcatndepletn": "964709", "insurance": "0", "othrexpnsa": "6223664", "othrexpnsb": "1116740", "othrexpnsc": "1005360", "othrexpnsd": "696475", "othrexpnse": "0", "othrexpnsf": "547997", "totfuncexpns": "12634373", "nonintcashend": "744069", "svngstempinvend": "0", "pldgegrntrcvblend": "0", "accntsrcvblend": "1287209", "currfrmrcvblend": "0", "rcvbldisqualend": "0", "notesloansrcvblend": "0", "invntriesalesend": "193938", "prepaidexpnsend": "1817330", "lndbldgsequipend": "25624816", "invstmntsend": "0", "invstmntsothrend": "0", "invstmntsprgmend": "4493137", "intangibleassetsend": "0", "othrassetsend": "0", "totassetsend": "34160499", "accntspayableend": "884588", "grntspayableend": "0", "deferedrevnuend": "24587", "txexmptbndsend": "0", "escrwaccntliabend": "0", "paybletoffcrsend": "0", "secrdmrtgsend": "11392281", "unsecurednotesend": "0", "othrliabend": "561463", "totliabend": "12862919", "unrstrctnetasstsend": "0", "temprstrctnetasstsend": "0", "permrstrctnetasstsend": "0", "capitalstktrstend": "2112669", "paidinsurplusend": "0", "retainedearnend": "19184911", "totnetassetend": "21297580", "totnetliabastend": "34160499", "nonpfrea": "", "totnooforgscnt": "0", "totsupport": "0", "gftgrntsrcvd170": "0", "txrevnuelevied170": "0", "srvcsval170": "0", "pubsuppsubtot170": "0", "exceeds2pct170": "0", "pubsupplesspct170": "0", "samepubsuppsubtot170": "0", "grsinc170": "0", "netincunreltd170": "0", "othrinc170": "0", "totsupp170": "0", "grsrcptsrelated170": "0", "totgftgrntrcvd509": "0", "grsrcptsadmissn509": "0", "grsrcptsactivities509": "0", "txrevnuelevied509": "0", "srvcsval509": "0", "pubsuppsubtot509": "0", "rcvdfrmdisqualsub509": "0", "exceeds1pct509": "0", "subtotpub509": "0", "pubsupplesub509": "0", "samepubsuppsubtot509": "0", "grsinc509": "0", "unreltxincls511tx509": "0", "subtotsuppinc509": "0", "netincunrelatd509": "0", "othrinc509": "0", "totsupp509": "0"}]