[{"\ufeffein": "611262016", "tax_pd": "201812", "subseccd": "3", "s501c3or4947a1cd": "Y", "schdbind": "Y", "politicalactvtscd": "N", "lbbyingactvtscd": "N", "subjto6033cd": "N", "dnradvisedfundscd": "N", "prptyintrcvdcd": "N", "maintwrkofartcd": "N", "crcounselingqstncd": "N", "hldassetsintermpermcd": "N", "rptlndbldgeqptcd": "Y", "rptinvstothsecd": "N", "rptinvstprgrelcd": "N", "rptothasstcd": "N", "rptothliabcd": "N", "sepcnsldtfinstmtcd": "Y", "sepindaudfinstmtcd": "Y", "inclinfinstmtcd": "N", "operateschools170cd": "N", "frgnofficecd": "N", "frgnrevexpnscd": "N", "frgngrntscd": "N", "frgnaggragrntscd": "N", "rptprofndrsngfeescd": "N", "rptincfnndrsngcd": "Y", "rptincgamingcd": "N", "operatehosptlcd": "N", "hospaudfinstmtcd": "N", "rptgrntstogovtcd": "N", "rptgrntstoindvcd": "N", "rptyestocompnstncd": "N", "txexmptbndcd": "N", "invstproceedscd": "N", "maintescrwaccntcd": "N", "actonbehalfcd": "N", "engageexcessbnftcd": "N", "awarexcessbnftcd": "N", "loantofficercd": "N", "grantoofficercd": "N", "dirbusnreltdcd": "N", "fmlybusnreltdcd": "N", "servasofficercd": "N", "recvnoncashcd": "Y", "recvartcd": "N", "ceaseoperationscd": "N", "sellorexchcd": "N", "ownsepentcd": "N", "reltdorgcd": "N", "intincntrlcd": "N", "orgtrnsfrcd": "N", "conduct5percentcd": "N", "compltschocd": "Y", "f1096cnt": "15", "fw2gcnt": "0", "wthldngrulescd": "Y", "noemplyeesw3cnt": "16", "filerqrdrtnscd": "Y", "unrelbusinccd": "N", "filedf990tcd": "N", "frgnacctcd": "N", "prohibtdtxshltrcd": "N", "prtynotifyorgcd": "N", "filedf8886tcd": "N", "solicitcntrbcd": "N", "exprstmntcd": "N", "providegoodscd": "N", "notfydnrvalcd": "N", "filedf8282cd": "N", "f8282cnt": "0", "fndsrcvdcd": "N", "premiumspaidcd": "N", "filedf8899cd": "N", "filedf1098ccd": "N", "excbushldngscd": "N", "s4966distribcd": "N", "distribtodonorcd": "N", "initiationfees": "0", "grsrcptspublicuse": "0", "grsincmembers": "0", "grsincother": "0", "filedlieuf1041cd": "N", "txexmptint": "0", "qualhlthplncd": "N", "qualhlthreqmntn": "0", "qualhlthonhnd": "0", "rcvdpdtngcd": "N", "filedf720cd": "N", "totreprtabled": "144032", "totcomprelatede": "0", "totestcompf": "15338", "noindiv100kcnt": "0", "nocontractor100kcnt": "0", "totcntrbgfts": "742605", "prgmservcode2acd": "624200", "totrev2acola": "45900", "prgmservcode2bcd": "624200", "totrev2bcola": "5900", "prgmservcode2ccd": "", "totrev2ccola": "0", "prgmservcode2dcd": "", "totrev2dcola": "0", "prgmservcode2ecd": "", "totrev2ecola": "0", "totrev2fcola": "0", "totprgmrevnue": "51800", "invstmntinc": "0", "txexmptbndsproceeds": "0", "royaltsinc": "0", "grsrntsreal": "22600", "grsrntsprsnl": "0", "rntlexpnsreal": "0", "rntlexpnsprsnl": "0", "rntlincreal": "22600", "rntlincprsnl": "0", "netrntlinc": "22600", "grsalesecur": "0", "grsalesothr": "1000", "cstbasisecur": "0", "cstbasisothr": "1719", "gnlsecur": "0", "gnlsothr": "-719", "netgnls": "-719", "grsincfndrsng": "44420", "lessdirfndrsng": "12083", "netincfndrsng": "32337", "grsincgaming": "0", "lessdirgaming": "0", "netincgaming": "0", "grsalesinvent": "74326", "lesscstofgoods": "41791", "netincsales": "32535", "miscrev11acd": "900099", "miscrevtota": "4572", "miscrev11bcd": "", "miscrevtot11b": "0", "miscrev11ccd": "", "miscrevtot11c": "0", "miscrevtot11d": "0", "miscrevtot11e": "4572", "totrevenue": "885730", "grntstogovt": "0", "grnsttoindiv": "0", "grntstofrgngovt": "0", "benifitsmembrs": "0", "compnsatncurrofcr": "144032", "compnsatnandothr": "0", "othrsalwages": "177111", "pensionplancontrb": "0", "othremplyeebenef": "36694", "payrolltx": "22523", "feesforsrvcmgmt": "0", "legalfees": "0", "accntingfees": "0", "feesforsrvclobby": "0", "profndraising": "0", "feesforsrvcinvstmgmt": "0", "feesforsrvcothr": "64882", "advrtpromo": "45791", "officexpns": "88634", "infotech": "48793", "royaltsexpns": "0", "occupancy": "30488", "travel": "58019", "travelofpublicoffcl": "0", "converconventmtng": "10159", "interestamt": "6033", "pymtoaffiliates": "0", "deprcatndepletn": "74048", "insurance": "21743", "othrexpnsa": "136655", "othrexpnsb": "99329", "othrexpnsc": "10219", "othrexpnsd": "0", "othrexpnse": "0", "othrexpnsf": "0", "totfuncexpns": "1075153", "nonintcashend": "244624", "svngstempinvend": "0", "pldgegrntrcvblend": "22701", "accntsrcvblend": "0", "currfrmrcvblend": "0", "rcvbldisqualend": "0", "notesloansrcvblend": "0", "invntriesalesend": "110758", "prepaidexpnsend": "0", "lndbldgsequipend": "1121270", "invstmntsend": "0", "invstmntsothrend": "0", "invstmntsprgmend": "0", "intangibleassetsend": "0", "othrassetsend": "12774", "totassetsend": "1512127", "accntspayableend": "24953", "grntspayableend": "0", "deferedrevnuend": "5400", "txexmptbndsend": "0", "escrwaccntliabend": "0", "paybletoffcrsend": "0", "secrdmrtgsend": "156422", "unsecurednotesend": "0", "othrliabend": "0", "totliabend": "186775", "unrstrctnetasstsend": "1214148", "temprstrctnetasstsend": "111204", "permrstrctnetasstsend": "0", "capitalstktrstend": "0", "paidinsurplusend": "0", "retainedearnend": "0", "totnetassetend": "1325352", "totnetliabastend": "1512127", "nonpfrea": "7", "totnooforgscnt": "0", "totsupport": "0", "gftgrntsrcvd170": "4460001", "txrevnuelevied170": "0", "srvcsval170": "0", "pubsuppsubtot170": "4460001", "exceeds2pct170": "419532", "pubsupplesspct170": "4040469", "samepubsuppsubtot170": "4460001", "grsinc170": "25570", "netincunreltd170": "0", "othrinc170": "34608", "totsupp170": "4520179", "grsrcptsrelated170": "411692", "totgftgrntrcvd509": "0", "grsrcptsadmissn509": "0", "grsrcptsactivities509": "0", "txrevnuelevied509": "0", "srvcsval509": "0", "pubsuppsubtot509": "0", "rcvdfrmdisqualsub509": "0", "exceeds1pct509": "0", "subtotpub509": "0", "pubsupplesub509": "0", "samepubsuppsubtot509": "0", "grsinc509": "0", "unreltxincls511tx509": "0", "subtotsuppinc509": "0", "netincunrelatd509": "0", "othrinc509": "0", "totsupp509": "0"}]